{
  "project_info": {
    "project_number": "282760367985",
    "project_id": "murojaah-159bb",
    "storage_bucket": "murojaah-159bb.appspot.com"
  },
  "client": [
    {
      "client_info": {
        "mobilesdk_app_id": "1:282760367985:android:e9c92dbfad8ad61983f0d0",
        "android_client_info": {
          "package_name": "com.murojaah.murojaah_mobile_7"
        }
      },
      "oauth_client": [
        {
          "client_id": "282760367985-m4p9n93938mcki3pk8i7i3s3bng4rgd0.apps.googleusercontent.com",
          "client_type": 3
        }
      ],
      "api_key": [
        {
          "current_key": "AIzaSyCPDq7NPHMysvvmCwaWnh0i5uPegpEXLPc"
        }
      ],
      "services": {
        "appinvite_service": {
          "other_platform_oauth_client": [
            {
              "client_id": "282760367985-m4p9n93938mcki3pk8i7i3s3bng4rgd0.apps.googleusercontent.com",
              "client_type": 3
            },
            {
              "client_id": "282760367985-4ifll0627p598vr5soe45blt8eletlbu.apps.googleusercontent.com",
              "client_type": 2,
              "ios_info": {
                "bundle_id": "com.murojaah.murojaah-mobile"
              }
            }
          ]
        }
      }
    }
  ],
  "configuration_version": "1"
}